<?xml version="1.0" ?><ItemLookupResponse xmlns="http://webservices.amazon.com/AWSECommerceService/2011-08-01"><OperationRequest><RequestId>6502883e-91ce-4b10-9fdc-a15ad3e98a89</RequestId><Arguments><Argument Name="AWSAccessKeyId" Value="AKIAIKNE7HGBQ57ABCQA"></Argument><Argument Name="AssociateTag" Value="vrbooks-20"></Argument><Argument Name="IdType" Value="ISBN"></Argument><Argument Name="ItemId" Value="0060097957"></Argument><Argument Name="Operation" Value="ItemLookup"></Argument><Argument Name="ResponseGroup" Value="Images,ItemAttributes"></Argument><Argument Name="SearchIndex" Value="Books"></Argument><Argument Name="Service" Value="AWSECommerceService"></Argument><Argument Name="Timestamp" Value="2016-05-28T22:17:55Z"></Argument><Argument Name="Signature" Value="ZUhF04F/ozRQK7BWj5rg3azjU5XgYgLGjdD3UIhDtGs="></Argument></Arguments><RequestProcessingTime>0.0826164240000000</RequestProcessingTime></OperationRequest><Items><Request><IsValid>True</IsValid><ItemLookupRequest><IdType>ISBN</IdType><ItemId>0060097957</ItemId><ResponseGroup>Images</ResponseGroup><ResponseGroup>ItemAttributes</ResponseGroup><SearchIndex>Books</SearchIndex><VariationPage>All</VariationPage></ItemLookupRequest></Request><Item><ASIN>0060097957</ASIN><DetailPageURL>http://www.amazon.com/Doubt-Doubters-Innovation-Jefferson-Dickinson/dp/0060097957%3FSubscriptionId%3DAKIAIKNE7HGBQ57ABCQA%26tag%3Dvrbooks-20%26linkCode%3Dxm2%26camp%3D2025%26creative%3D165953%26creativeASIN%3D0060097957</DetailPageURL><ItemLinks><ItemLink><Description>Technical Details</Description><URL>http://www.amazon.com/Doubt-Doubters-Innovation-Jefferson-Dickinson/dp/tech-data/0060097957%3FSubscriptionId%3DAKIAIKNE7HGBQ57ABCQA%26tag%3Dvrbooks-20%26linkCode%3Dxm2%26camp%3D2025%26creative%3D386001%26creativeASIN%3D0060097957</URL></ItemLink><ItemLink><Description>Add To Baby Registry</Description><URL>http://www.amazon.com/gp/registry/baby/add-item.html%3Fasin.0%3D0060097957%26SubscriptionId%3DAKIAIKNE7HGBQ57ABCQA%26tag%3Dvrbooks-20%26linkCode%3Dxm2%26camp%3D2025%26creative%3D386001%26creativeASIN%3D0060097957</URL></ItemLink><ItemLink><Description>Add To Wedding Registry</Description><URL>http://www.amazon.com/gp/registry/wedding/add-item.html%3Fasin.0%3D0060097957%26SubscriptionId%3DAKIAIKNE7HGBQ57ABCQA%26tag%3Dvrbooks-20%26linkCode%3Dxm2%26camp%3D2025%26creative%3D386001%26creativeASIN%3D0060097957</URL></ItemLink><ItemLink><Description>Add To Wishlist</Description><URL>http://www.amazon.com/gp/registry/wishlist/add-item.html%3Fasin.0%3D0060097957%26SubscriptionId%3DAKIAIKNE7HGBQ57ABCQA%26tag%3Dvrbooks-20%26linkCode%3Dxm2%26camp%3D2025%26creative%3D386001%26creativeASIN%3D0060097957</URL></ItemLink><ItemLink><Description>Tell A Friend</Description><URL>http://www.amazon.com/gp/pdp/taf/0060097957%3FSubscriptionId%3DAKIAIKNE7HGBQ57ABCQA%26tag%3Dvrbooks-20%26linkCode%3Dxm2%26camp%3D2025%26creative%3D386001%26creativeASIN%3D0060097957</URL></ItemLink><ItemLink><Description>All Customer Reviews</Description><URL>http://www.amazon.com/review/product/0060097957%3FSubscriptionId%3DAKIAIKNE7HGBQ57ABCQA%26tag%3Dvrbooks-20%26linkCode%3Dxm2%26camp%3D2025%26creative%3D386001%26creativeASIN%3D0060097957</URL></ItemLink><ItemLink><Description>All Offers</Description><URL>http://www.amazon.com/gp/offer-listing/0060097957%3FSubscriptionId%3DAKIAIKNE7HGBQ57ABCQA%26tag%3Dvrbooks-20%26linkCode%3Dxm2%26camp%3D2025%26creative%3D386001%26creativeASIN%3D0060097957</URL></ItemLink></ItemLinks><SmallImage><URL>http://ecx.images-amazon.com/images/I/41NzmyC3IwL._SL75_.jpg</URL><Height Units="pixels">75</Height><Width Units="pixels">50</Width></SmallImage><MediumImage><URL>http://ecx.images-amazon.com/images/I/41NzmyC3IwL._SL160_.jpg</URL><Height Units="pixels">160</Height><Width Units="pixels">107</Width></MediumImage><LargeImage><URL>http://ecx.images-amazon.com/images/I/41NzmyC3IwL.jpg</URL><Height Units="pixels">500</Height><Width Units="pixels">333</Width></LargeImage><ImageSets><ImageSet Category="primary"><SwatchImage><URL>http://ecx.images-amazon.com/images/I/41NzmyC3IwL._SL30_.jpg</URL><Height Units="pixels">30</Height><Width Units="pixels">20</Width></SwatchImage><SmallImage><URL>http://ecx.images-amazon.com/images/I/41NzmyC3IwL._SL75_.jpg</URL><Height Units="pixels">75</Height><Width Units="pixels">50</Width></SmallImage><ThumbnailImage><URL>http://ecx.images-amazon.com/images/I/41NzmyC3IwL._SL75_.jpg</URL><Height Units="pixels">75</Height><Width Units="pixels">50</Width></ThumbnailImage><TinyImage><URL>http://ecx.images-amazon.com/images/I/41NzmyC3IwL._SL110_.jpg</URL><Height Units="pixels">110</Height><Width Units="pixels">73</Width></TinyImage><MediumImage><URL>http://ecx.images-amazon.com/images/I/41NzmyC3IwL._SL160_.jpg</URL><Height Units="pixels">160</Height><Width Units="pixels">107</Width></MediumImage><LargeImage><URL>http://ecx.images-amazon.com/images/I/41NzmyC3IwL.jpg</URL><Height Units="pixels">500</Height><Width Units="pixels">333</Width></LargeImage></ImageSet></ImageSets><ItemAttributes><Author>Jennifer Michael Hecht</Author><Binding>Paperback</Binding><Brand>HarperOne</Brand><EAN>9780060097950</EAN><EANList><EANListElement>9780060097950</EANListElement></EANList><Edition>Reprint</Edition><Feature>Great product!</Feature><ISBN>0060097957</ISBN><ItemDimensions><Height Units="hundredths-inches">900</Height><Length Units="hundredths-inches">600</Length><Weight Units="hundredths-pounds">136</Weight><Width Units="hundredths-inches">144</Width></ItemDimensions><Label>HarperOne</Label><Languages><Language><Name>English</Name><Type>Published</Type></Language><Language><Name>English</Name><Type>Original Language</Type></Language><Language><Name>English</Name><Type>Unknown</Type></Language></Languages><ListPrice><Amount>1699</Amount><CurrencyCode>USD</CurrencyCode><FormattedPrice>$16.99</FormattedPrice></ListPrice><Manufacturer>HarperOne</Manufacturer><NumberOfItems>1</NumberOfItems><NumberOfPages>576</NumberOfPages><PackageDimensions><Height Units="hundredths-inches">160</Height><Length Units="hundredths-inches">890</Length><Weight Units="hundredths-pounds">115</Weight><Width Units="hundredths-inches">600</Width></PackageDimensions><PackageQuantity>1</PackageQuantity><ProductGroup>Book</ProductGroup><ProductTypeName>ABIS_BOOK</ProductTypeName><PublicationDate>2004-09-07</PublicationDate><Publisher>HarperOne</Publisher><ReleaseDate>2004-09-07</ReleaseDate><Studio>HarperOne</Studio><Title>Doubt: A History: The Great Doubters and Their Legacy of Innovation from Socrates and Jesus to Thomas Jefferson and Emily Dickinson</Title></ItemAttributes></Item><Item><ASIN>B004SCXVOI</ASIN><DetailPageURL>http://www.amazon.com/Doubt-Publisher-Jennifer-Michael-Hecht/dp/B004SCXVOI%3FSubscriptionId%3DAKIAIKNE7HGBQ57ABCQA%26tag%3Dvrbooks-20%26linkCode%3Dxm2%26camp%3D2025%26creative%3D165953%26creativeASIN%3DB004SCXVOI</DetailPageURL><ItemLinks><ItemLink><Description>Technical Details</Description><URL>http://www.amazon.com/Doubt-Publisher-Jennifer-Michael-Hecht/dp/tech-data/B004SCXVOI%3FSubscriptionId%3DAKIAIKNE7HGBQ57ABCQA%26tag%3Dvrbooks-20%26linkCode%3Dxm2%26camp%3D2025%26creative%3D386001%26creativeASIN%3DB004SCXVOI</URL></ItemLink><ItemLink><Description>Add To Baby Registry</Description><URL>http://www.amazon.com/gp/registry/baby/add-item.html%3Fasin.0%3DB004SCXVOI%26SubscriptionId%3DAKIAIKNE7HGBQ57ABCQA%26tag%3Dvrbooks-20%26linkCode%3Dxm2%26camp%3D2025%26creative%3D386001%26creativeASIN%3DB004SCXVOI</URL></ItemLink><ItemLink><Description>Add To Wedding Registry</Description><URL>http://www.amazon.com/gp/registry/wedding/add-item.html%3Fasin.0%3DB004SCXVOI%26SubscriptionId%3DAKIAIKNE7HGBQ57ABCQA%26tag%3Dvrbooks-20%26linkCode%3Dxm2%26camp%3D2025%26creative%3D386001%26creativeASIN%3DB004SCXVOI</URL></ItemLink><ItemLink><Description>Add To Wishlist</Description><URL>http://www.amazon.com/gp/registry/wishlist/add-item.html%3Fasin.0%3DB004SCXVOI%26SubscriptionId%3DAKIAIKNE7HGBQ57ABCQA%26tag%3Dvrbooks-20%26linkCode%3Dxm2%26camp%3D2025%26creative%3D386001%26creativeASIN%3DB004SCXVOI</URL></ItemLink><ItemLink><Description>Tell A Friend</Description><URL>http://www.amazon.com/gp/pdp/taf/B004SCXVOI%3FSubscriptionId%3DAKIAIKNE7HGBQ57ABCQA%26tag%3Dvrbooks-20%26linkCode%3Dxm2%26camp%3D2025%26creative%3D386001%26creativeASIN%3DB004SCXVOI</URL></ItemLink><ItemLink><Description>All Customer Reviews</Description><URL>http://www.amazon.com/review/product/B004SCXVOI%3FSubscriptionId%3DAKIAIKNE7HGBQ57ABCQA%26tag%3Dvrbooks-20%26linkCode%3Dxm2%26camp%3D2025%26creative%3D386001%26creativeASIN%3DB004SCXVOI</URL></ItemLink><ItemLink><Description>All Offers</Description><URL>http://www.amazon.com/gp/offer-listing/B004SCXVOI%3FSubscriptionId%3DAKIAIKNE7HGBQ57ABCQA%26tag%3Dvrbooks-20%26linkCode%3Dxm2%26camp%3D2025%26creative%3D386001%26creativeASIN%3DB004SCXVOI</URL></ItemLink></ItemLinks><SmallImage><URL>http://ecx.images-amazon.com/images/I/31d7y4V8OPL._SL75_.jpg</URL><Height Units="pixels">75</Height><Width Units="pixels">50</Width></SmallImage><MediumImage><URL>http://ecx.images-amazon.com/images/I/31d7y4V8OPL._SL160_.jpg</URL><Height Units="pixels">160</Height><Width Units="pixels">107</Width></MediumImage><LargeImage><URL>http://ecx.images-amazon.com/images/I/31d7y4V8OPL.jpg</URL><Height Units="pixels">276</Height><Width Units="pixels">185</Width></LargeImage><ImageSets><ImageSet Category="primary"><SwatchImage><URL>http://ecx.images-amazon.com/images/I/31d7y4V8OPL._SL30_.jpg</URL><Height Units="pixels">30</Height><Width Units="pixels">20</Width></SwatchImage><SmallImage><URL>http://ecx.images-amazon.com/images/I/31d7y4V8OPL._SL75_.jpg</URL><Height Units="pixels">75</Height><Width Units="pixels">50</Width></SmallImage><ThumbnailImage><URL>http://ecx.images-amazon.com/images/I/31d7y4V8OPL._SL75_.jpg</URL><Height Units="pixels">75</Height><Width Units="pixels">50</Width></ThumbnailImage><TinyImage><URL>http://ecx.images-amazon.com/images/I/31d7y4V8OPL._SL110_.jpg</URL><Height Units="pixels">110</Height><Width Units="pixels">74</Width></TinyImage><MediumImage><URL>http://ecx.images-amazon.com/images/I/31d7y4V8OPL._SL160_.jpg</URL><Height Units="pixels">160</Height><Width Units="pixels">107</Width></MediumImage><LargeImage><URL>http://ecx.images-amazon.com/images/I/31d7y4V8OPL.jpg</URL><Height Units="pixels">276</Height><Width Units="pixels">185</Width></LargeImage></ImageSet></ImageSets><ItemAttributes><Author>Jennifer Michael Hecht</Author><Binding>Paperback</Binding><EAN>9780060097950</EAN><EANList><EANListElement>9780060097950</EANListElement></EANList><ISBN>0060097957</ISBN><ProductGroup>Book</ProductGroup><ProductTypeName>BOOKS_1973_AND_LATER</ProductTypeName><PublicationDate>2004</PublicationDate><Title>Doubt Publisher: HarperOne</Title></ItemAttributes></Item><Item><ASIN>B003YCOORG</ASIN><DetailPageURL>http://www.amazon.com/Doubt-Doubters-Innovation-Jefferson-Dickinson-ebook/dp/B003YCOORG%3FSubscriptionId%3DAKIAIKNE7HGBQ57ABCQA%26tag%3Dvrbooks-20%26linkCode%3Dxm2%26camp%3D2025%26creative%3D165953%26creativeASIN%3DB003YCOORG</DetailPageURL><ItemLinks><ItemLink><Description>Technical Details</Description><URL>http://www.amazon.com/Doubt-Doubters-Innovation-Jefferson-Dickinson-ebook/dp/tech-data/B003YCOORG%3FSubscriptionId%3DAKIAIKNE7HGBQ57ABCQA%26tag%3Dvrbooks-20%26linkCode%3Dxm2%26camp%3D2025%26creative%3D386001%26creativeASIN%3DB003YCOORG</URL></ItemLink><ItemLink><Description>Add To Baby Registry</Description><URL>http://www.amazon.com/gp/registry/baby/add-item.html%3Fasin.0%3DB003YCOORG%26SubscriptionId%3DAKIAIKNE7HGBQ57ABCQA%26tag%3Dvrbooks-20%26linkCode%3Dxm2%26camp%3D2025%26creative%3D386001%26creativeASIN%3DB003YCOORG</URL></ItemLink><ItemLink><Description>Add To Wedding Registry</Description><URL>http://www.amazon.com/gp/registry/wedding/add-item.html%3Fasin.0%3DB003YCOORG%26SubscriptionId%3DAKIAIKNE7HGBQ57ABCQA%26tag%3Dvrbooks-20%26linkCode%3Dxm2%26camp%3D2025%26creative%3D386001%26creativeASIN%3DB003YCOORG</URL></ItemLink><ItemLink><Description>Add To Wishlist</Description><URL>http://www.amazon.com/gp/registry/wishlist/add-item.html%3Fasin.0%3DB003YCOORG%26SubscriptionId%3DAKIAIKNE7HGBQ57ABCQA%26tag%3Dvrbooks-20%26linkCode%3Dxm2%26camp%3D2025%26creative%3D386001%26creativeASIN%3DB003YCOORG</URL></ItemLink><ItemLink><Description>Tell A Friend</Description><URL>http://www.amazon.com/gp/pdp/taf/B003YCOORG%3FSubscriptionId%3DAKIAIKNE7HGBQ57ABCQA%26tag%3Dvrbooks-20%26linkCode%3Dxm2%26camp%3D2025%26creative%3D386001%26creativeASIN%3DB003YCOORG</URL></ItemLink><ItemLink><Description>All Customer Reviews</Description><URL>http://www.amazon.com/review/product/B003YCOORG%3FSubscriptionId%3DAKIAIKNE7HGBQ57ABCQA%26tag%3Dvrbooks-20%26linkCode%3Dxm2%26camp%3D2025%26creative%3D386001%26creativeASIN%3DB003YCOORG</URL></ItemLink><ItemLink><Description>All Offers</Description><URL>http://www.amazon.com/gp/offer-listing/B003YCOORG%3FSubscriptionId%3DAKIAIKNE7HGBQ57ABCQA%26tag%3Dvrbooks-20%26linkCode%3Dxm2%26camp%3D2025%26creative%3D386001%26creativeASIN%3DB003YCOORG</URL></ItemLink></ItemLinks><SmallImage><URL>http://ecx.images-amazon.com/images/I/415qJRmfdtL._SL75_.jpg</URL><Height Units="pixels">75</Height><Width Units="pixels">50</Width></SmallImage><MediumImage><URL>http://ecx.images-amazon.com/images/I/415qJRmfdtL._SL160_.jpg</URL><Height Units="pixels">160</Height><Width Units="pixels">107</Width></MediumImage><LargeImage><URL>http://ecx.images-amazon.com/images/I/415qJRmfdtL.jpg</URL><Height Units="pixels">500</Height><Width Units="pixels">335</Width></LargeImage><ImageSets><ImageSet Category="primary"><SwatchImage><URL>http://ecx.images-amazon.com/images/I/415qJRmfdtL._SL30_.jpg</URL><Height Units="pixels">30</Height><Width Units="pixels">20</Width></SwatchImage><SmallImage><URL>http://ecx.images-amazon.com/images/I/415qJRmfdtL._SL75_.jpg</URL><Height Units="pixels">75</Height><Width Units="pixels">50</Width></SmallImage><ThumbnailImage><URL>http://ecx.images-amazon.com/images/I/415qJRmfdtL._SL75_.jpg</URL><Height Units="pixels">75</Height><Width Units="pixels">50</Width></ThumbnailImage><TinyImage><URL>http://ecx.images-amazon.com/images/I/415qJRmfdtL._SL110_.jpg</URL><Height Units="pixels">110</Height><Width Units="pixels">74</Width></TinyImage><MediumImage><URL>http://ecx.images-amazon.com/images/I/415qJRmfdtL._SL160_.jpg</URL><Height Units="pixels">160</Height><Width Units="pixels">107</Width></MediumImage><LargeImage><URL>http://ecx.images-amazon.com/images/I/415qJRmfdtL.jpg</URL><Height Units="pixels">500</Height><Width Units="pixels">335</Width></LargeImage></ImageSet></ImageSets><ItemAttributes><Author>Jennifer Hecht</Author><Binding>Kindle Edition</Binding><EISBN>9780062031396</EISBN><Format>Kindle eBook</Format><Label>HarperCollins e-books</Label><Languages><Language><Name>English</Name><Type>Published</Type></Language></Languages><Manufacturer>HarperCollins e-books</Manufacturer><NumberOfPages>576</NumberOfPages><ProductGroup>eBooks</ProductGroup><ProductTypeName>ABIS_EBOOKS</ProductTypeName><PublicationDate>2010-09-28</PublicationDate><Publisher>HarperCollins e-books</Publisher><ReleaseDate>2010-09-28</ReleaseDate><Studio>HarperCollins e-books</Studio><Title>Doubt: A History: The Great Doubters and Their Legacy of Innovation from Socrates and Jesus to Thomas Jefferson and Emily Dickinson</Title></ItemAttributes></Item></Items></ItemLookupResponse>